{
    "dark": [
        "#0f101a",
        "#0f101a"
    ],
    "grey": [
        "#37383b",
        "#37383b"
    ],
    "light": [
        "#f1ffff",
        "#f1ffff"
    ],
    "text": [
        "#f1ffff",
        "#f1ffff"
    ],
    "focus": [
        "#66818d",
        "#66818d"
    ],
    "active": [
        "#f1ffff",
        "#f1ffff"
    ],
    "inactive": [
        "#4c566a",
        "#4c566a"
    ],
    "urgent": [
        "#3f575b",
        "#3f575b"
    ],
    "color1": [
        "#0f101a",
        "#0f101a"
    ],
    "color2": [
        "#334148",
        "#334148"
    ],
    "color3": [
        "#3f575b",
        "#3f575b"
    ],
    "color4": [
        "#556a74",
        "#556a74"
    ]
}
